seismic/__index__.py
seismic/logfactory.py
seismic/correlate/__index__.py
seismic/correlate/correlate.py
seismic/correlate/preprocessing_fd.py
seismic/correlate/preprocessing_stream.py
seismic/correlate/preprocessing_td.py
seismic/correlate/stats.py
seismic/correlate/stream.py
seismic/db/__index__.py
seismic/db/corr_hdf5.py
seismic/monitor/__index__.py
seismic/monitor/dv.py
seismic/monitor/monitor.py
seismic/monitor/post_corr_process.py
seismic/monitor/spatial.py
seismic/monitor/stretch_mod.py
seismic/monitor/trim.py
seismic/monitor/wfc.py
seismic/plot/__index__.py
seismic/plot/batlow.txt
seismic/plot/plot_correlation.py
seismic/plot/plot_dv.py
seismic/plot/plot_multidv.py
seismic/plot/plot_spectrum.py
seismic/plot/plot_utils.py
seismic/plot/plot_wfc.py
seismic/trace_data/__index__.py
seismic/trace_data/waveform.py
seismic/utils/__index__.py
seismic/utils/fetch_func_from_str.py
seismic/utils/io.py
seismic/utils/miic_utils.py
seismic/utils/raw_analysis.py
seismic/utils/roundhalf.py
seismic-0.6.19.dist-info/licenses/LICENSE
seismic-0.6.19.dist-info/METADATA
seismic-0.6.19.dist-info/WHEEL
seismic-0.6.19.dist-info/top_level.txt
seismic-0.6.19.dist-info/RECORD
