Metadata-Version: 2.4
Name: seismic
Version: 0.6.19
Summary: Seismological Monitoring using Interferometric Concepts
Home-page: https://github.com/PeterMakus/SeisMIC
Author: Peter Makus, Christoph Sens-Schönfelder, Johanna Lehr, and the SeisMIC development team
Author-email: makus@gfz-potsdam.de
Project-URL: Documentation, https://petermakus.github.io/SeisMIC/index.html
Project-URL: doi, https://doi.org/10.26443/seismica.v3i1.1099
Keywords: Seismology,Ambient Noise,Earth Sciences,Environmental Seismology,Volcano Seismology,Critical Zone,Time-dependent dynamics,Inteferometry,Monitoring,Structural Health
Classifier: Programming Language :: Python :: 3
Classifier: License :: OSI Approved :: European Union Public Licence 1.2 (EUPL 1.2)
Classifier: Operating System :: OS Independent
Classifier: Development Status :: 4 - Beta
Classifier: Topic :: Utilities
Requires-Python: <=3.13,>=3.10
License-File: LICENSE
Requires-Dist: geographiclib==2.0
Requires-Dist: h5py<=3.12.1
Requires-Dist: matplotlib<=3.8.4
Requires-Dist: mpi4py<=4.0.1
Requires-Dist: numpy<=1.26.4
Requires-Dist: obspy<=1.4.1,>=1.3.1
Requires-Dist: pip
Requires-Dist: prov
Requires-Dist: pyyaml
Requires-Dist: scipy<=1.15.0
Requires-Dist: flake8
Requires-Dist: tqdm
Provides-Extra: docs
Requires-Dist: sphinx<6.0; extra == "docs"
Requires-Dist: pydata-sphinx-theme; extra == "docs"
Requires-Dist: sphinx-copybutton; extra == "docs"
Requires-Dist: sphinxcontrib-mermaid; extra == "docs"
Requires-Dist: jinja2<3.1; extra == "docs"
Requires-Dist: jupyter; extra == "docs"
Provides-Extra: tests
Requires-Dist: pytest; extra == "tests"
Requires-Dist: py; extra == "tests"
Requires-Dist: flake8; extra == "tests"
Dynamic: license-file
